odoo/addons/purchase_deposit/README.rst
odoo/addons/purchase_deposit/__init__.py
odoo/addons/purchase_deposit/__manifest__.py
odoo/addons/purchase_deposit/i18n/es_MX.po
odoo/addons/purchase_deposit/i18n/pt.po
odoo/addons/purchase_deposit/i18n/purchase_deposit.pot
odoo/addons/purchase_deposit/models/__init__.py
odoo/addons/purchase_deposit/models/invoice.py
odoo/addons/purchase_deposit/models/purchase.py
odoo/addons/purchase_deposit/models/res_config_settings.py
odoo/addons/purchase_deposit/readme/CONFIGURATION.rst
odoo/addons/purchase_deposit/readme/CONTRIBUTORS.rst
odoo/addons/purchase_deposit/readme/DESCRIPTION.rst
odoo/addons/purchase_deposit/readme/USAGE.rst
odoo/addons/purchase_deposit/static/description/icon.png
odoo/addons/purchase_deposit/static/description/index.html
odoo/addons/purchase_deposit/tests/__init__.py
odoo/addons/purchase_deposit/tests/test_purchase_deposit.py
odoo/addons/purchase_deposit/views/purchase_view.xml
odoo/addons/purchase_deposit/views/res_config_settings_views.xml
odoo/addons/purchase_deposit/wizard/__init__.py
odoo/addons/purchase_deposit/wizard/purchase_make_invoice_advance.py
odoo/addons/purchase_deposit/wizard/purchase_make_invoice_advance_views.xml
odoo12_addon_purchase_deposit-12.0.1.0.0.99.dev10.dist-info/METADATA
odoo12_addon_purchase_deposit-12.0.1.0.0.99.dev10.dist-info/WHEEL
odoo12_addon_purchase_deposit-12.0.1.0.0.99.dev10.dist-info/top_level.txt
odoo12_addon_purchase_deposit-12.0.1.0.0.99.dev10.dist-info/RECORD
